iot_to_linkml/__init__.py
iot_to_linkml/becli.py
iot_to_linkml/sheet2yaml.py
iot_to_linkml-0.1.21.dist-info/entry_points.txt
iot_to_linkml-0.1.21.dist-info/WHEEL
iot_to_linkml-0.1.21.dist-info/METADATA
iot_to_linkml-0.1.21.dist-info/RECORD
