Metadata-Version: 2.1
Name: iot-to-linkml
Version: 0.1.21
Summary: see https://github.com/microbiomedata/IoT_to_linkml
Author: Mark A. Miller
Author-email: mamillerpa@gmail.com
Requires-Python: >=3.9,<4.0
Classifier: Programming Language :: Python :: 3
Classifier: Programming Language :: Python :: 3.9
Requires-Dist: click
Requires-Dist: google-api-python-client (>=2.30.0,<3.0.0)
Requires-Dist: google-auth-oauthlib (>=0.4.6,<0.5.0)
Requires-Dist: linkml (>=1.1.12,<2.0.0)
Requires-Dist: linkml-runtime (>=1.1.6,<2.0.0)
Requires-Dist: pandas (>=1.3.4,<2.0.0)
Requires-Dist: pyaml (>=21.10.1,<22.0.0)
